<?xml version="1.0" encoding="UTF-8"?>
<DefaultStyles>
    <base family="sans-serif" fontSize="18" />
    <style name="Regular Paragraph" allowHyphenations="true" firstLineIndentDelta="dpi*0.12"
        id="0" />
    <style name="Title" alignment="center" allowHyphenations="false" bold="true" fontSizeDelta="10" id="1"
        spaceAfter="7" spaceBefore="2" />
    <style name="Poem Title" allowHyphenations="false" bold="true" fontSizeDelta="2" id="3" leftIndent="40"
        spaceAfter="6" spaceBefore="6" />
    <style name="Section Title" alignment="center" allowHyphenations="false" bold="true" fontSizeDelta="6"
        id="2" spaceAfter="5" />
    <style name="Header 1" alignment="center" allowHyphenations="false" bold="true" fontSizeDelta="6" id="31"
        spaceAfter="5" />
    <style name="Header 2" alignment="center" allowHyphenations="false" bold="true" fontSizeDelta="6" id="32"
        spaceAfter="5" />
    <style name="Annotation" allowHyphenations="true" firstLineIndentDelta="dpi*0.12" fontSizeDelta="-2"
        id="5" />
    <style name="Epigraph" allowHyphenations="true" fontSizeDelta="-2" id="6" italic="true"
        leftIndent="80" />
    <style name="Subtitle" allowHyphenations="true" bold="true" id="4" />
    <style name="Header 3" allowHyphenations="true" bold="true" id="33" />
    <style name="Header 4" allowHyphenations="true" bold="true" id="34" />
    <style name="Author" allowHyphenations="false" id="13" leftIndent="20" />
    <style name="Date" allowHyphenations="false" id="14" leftIndent="40" />
    <style name="Stanza" alignment="left" allowHyphenations="false" id="7" spaceAfter="6"
        spaceBefore="6" />
    <style name="Verse" alignment="left" allowHyphenations="false" id="8" leftIndent="20" />
    <style name="Image" alignment="center" id="10" spaceBefore="8" />
    <style name="Preformatted text" alignment="left" allowHyphenations="false" id="9"
        italic="true" />

    <style name="Cite" id="12" italic="true" partial="true" />
    <style name="Internal Hyperlink" allowHyphenations="false" id="15" partial="true"
        underline="true" />
    <style name="External Hyperlink" allowHyphenations="false" id="37" partial="true"
        underline="true" />
    <style name="Footnote" allowHyphenations="false" fontSizeDelta="-5" id="16" partial="true"
        vShift="7" />
    <style name="Emphasis" id="17" italic="true" partial="true" />
    <style name="Strong" bold="true" id="18" partial="true" />
    <style name="Header 5" bold="true" id="35" />
    <style name="Header 6" bold="true" id="36" />
    <style name="Subscript" allowHyphenations="false" fontSizeDelta="-4" id="19" partial="true"
        vShift="-4" />
    <style name="Superscript" allowHyphenations="false" fontSizeDelta="-4" id="20" partial="true"
        vShift="10" />
    <style name="Code" allowHyphenations="false" id="21" italic="true" partial="true" />
    <style name="StrikeThrough" id="22" partial="true" strikeThrough="true" />
    <style name="Italic" id="27" italic="true" partial="true" />
    <style name="Bold" bold="true" id="28" partial="true" />
    <style name="Definition" id="29" italic="true" partial="true" />
    <style name="Definition Description" id="30" italic="true" partial="true" />
</DefaultStyles>
